dashboard_probability/GuiTest1.py
dashboard_probability/Tree.py
dashboard_probability/dashboard_probability.py
your_win/GuiTest1.py
your_win/Tree.py
your_win/setup.py
your_win/your_win.py
your_win-0.1.5.dist-info/METADATA
your_win-0.1.5.dist-info/WHEEL
your_win-0.1.5.dist-info/top_level.txt
your_win-0.1.5.dist-info/RECORD
