Metadata-Version: 2.1
Name: your-win
Version: 0.1.5
Summary: A package of rare tools for analyzing random numbers in a flexible and entertaining way quick start roulette slots game
Home-page: UNKNOWN
Author: io_OFast
Author-email: mahmoudorabi4633346@gmail.com
License: MIT
Platform: UNKNOWN
Classifier: License :: OSI Approved :: MIT License
Classifier: Programming Language :: Python :: 2
Classifier: Programming Language :: Python :: 3
